diagram2vec/__init__.py
diagram2vec/diagram2vec.py
diagram2vec-0.0.2.dist-info/LICENSE
diagram2vec-0.0.2.dist-info/METADATA
diagram2vec-0.0.2.dist-info/WHEEL
diagram2vec-0.0.2.dist-info/top_level.txt
diagram2vec-0.0.2.dist-info/RECORD
