Metadata-Version: 2.1
Name: diagram2vec
Version: 0.0.2
Summary: Vector Representations of Persistence Diagrams
Home-page: https://github.com/oleg-kachan/diagram2vec
Author: Oleg Kachan
Author-email: oleg.n.kachan@gmail.com
License: UNKNOWN
Platform: UNKNOWN
Classifier: Programming Language :: Python :: 3
Classifier: License :: OSI Approved :: MIT License
Classifier: Operating System :: OS Independent
Requires-Python: >=3.6
